PythonSed/__init__.py
PythonSed/sed.py
pythonsed-2.1.post0.dist-info/METADATA
pythonsed-2.1.post0.dist-info/WHEEL
pythonsed-2.1.post0.dist-info/entry_points.txt
pythonsed-2.1.post0.dist-info/licenses/LICENSE
pythonsed-2.1.post0.dist-info/RECORD
