Metadata-Version: 2.1
Name: pythonsed
Version: 2.1.post0
Summary: This package delivers a fully GNU sed compatible sed implementation in Python.
Project-URL: Homepage, https://github.com/fschaeck/PythonSed
Project-URL: Bug Tracker, https://github.com/fschaeck/PythonSed/issues
Author-email: Frank Schäckermann <pypi-fschaeckermann@snkmail.com>
License-File: LICENSE
Keywords: GNU sed,sed,stream editor
Classifier: Development Status :: 5 - Production/Stable
Classifier: Environment :: Console
Classifier: Intended Audience :: End Users/Desktop
Classifier: License :: OSI Approved :: GNU General Public License v3 (GPLv3)
Classifier: Operating System :: OS Independent
Classifier: Programming Language :: Python :: 2.7
Classifier: Programming Language :: Python :: 3
Classifier: Topic :: Utilities
Requires-Python: >=2.7
